fastapi_authkit/__init__.py
fastapi_authkit/base.py
fastapi_authkit/settings.py
fastapi_authkit/utils.py
fastapi_authkit/core/__init__.py
fastapi_authkit/core/oauth.py
fastapi_authkit/core/providers.py
fastapi_authkit/interfaces/__init__.py
fastapi_authkit/interfaces/logics.py
fastapi_authkit/interfaces/provider.py
fastapi_authkit-0.0.2.dist-info/LICENSE
fastapi_authkit-0.0.2.dist-info/METADATA
fastapi_authkit-0.0.2.dist-info/WHEEL
fastapi_authkit-0.0.2.dist-info/top_level.txt
fastapi_authkit-0.0.2.dist-info/RECORD
