Metadata-Version: 2.1
Name: fastapi-authkit
Version: 0.0.2
Summary: FastAPI-authkit is an extenstion to provide oauth-oidc authentication/authorization and user management for fastapi.
Home-page: https://github.com/Anbarryprojects/fastapi-authkit
Author: Parsa Pourmohammad
Author-email: parsapourmohammad1999@gmail.com
Maintainer: Anbarryprojects
License: MIT
Project-URL: Documentation, https://github.com/Anbarryprojects/fastapi-authkit
Project-URL: Source Code, https://github.com/Anbarryprojects/fastapi-authkit
Project-URL: Issue Tracker, https://github.com/Anbarryprojects/fastapi-authkit/issues/
Classifier: Development Status :: 3 - Alpha
Classifier: Environment :: Web Environment
Classifier: Framework :: FastAPI
Classifier: Intended Audience :: Developers
Classifier: Topic :: Internet :: WWW/HTTP :: Dynamic Content
Classifier: Topic :: Software Development :: Libraries :: Application Frameworks
Classifier: Programming Language :: Python :: 3
Classifier: License :: OSI Approved :: MIT License
Classifier: Operating System :: OS Independent
Requires-Python: >=3.7
License-File: LICENSE
Requires-Dist: fastapi
Requires-Dist: uvicorn
Requires-Dist: Authlib
Requires-Dist: itsdangerous
Requires-Dist: passlib
Requires-Dist: python-dotenv
